cli/__init__.py
cli/dataset_manager.py
dataset_management/__init__.py
dataset_management/blob.py
dataset_management/connection_provider.py
dataset_management/dataset.py
dataset_management/triggers.py
dataset_management/utils.py
dataset_manager/__init__.py
dataset_manager/dataset_manager.py
dataset_manager/utils/__init__.py
dataset_manager/utils/image_util.py
dm_modules/__init__.py
dm_modules/analytics_dao/__init__.py
dm_modules/analytics_dao/db.py
dm_modules/analytics_dao/dbms.py
dm_modules/analytics_dao/groundtruth_dao.py
dm_modules/analytics_dao/groundtruth_scheme.py
dm_modules/analytics_dao/gservice_dao.py
dm_modules/analytics_dao/metadata_dao.py
dm_modules/analytics_dao/metadata_scheme.py
dm_modules/analytics_dao/migrate.py
dm_modules/analytics_dao/moap_execution_dao.py
dm_modules/analytics_dao/parser.py
dm_modules/analytics_dao/prediction_dao.py
dm_modules/analytics_dao/prediction_scheme.py
dm_modules/analytics_dao/scanner.py
dm_modules/analytics_dao/validator.py
dm_modules/analytics_dao/utils/__init__.py
dm_modules/analytics_dao/utils/coord_utils.py
dm_modules/analytics_dao/utils/module_utils.py
dm_modules/analytics_dao/utils/validator_utils.py
mlmd/__init__.py
mlmd/dataset_manager_dao.py
mlmd/dataset_manager_scheme.py
mlmd/metadata_dao.py
mlmd_dataset_management-2.3.10.dist-info/METADATA
mlmd_dataset_management-2.3.10.dist-info/WHEEL
mlmd_dataset_management-2.3.10.dist-info/entry_points.txt
mlmd_dataset_management-2.3.10.dist-info/top_level.txt
mlmd_dataset_management-2.3.10.dist-info/RECORD
