Metadata-Version: 2.1
Name: mlmd-dataset-management
Version: 2.3.10
Summary: MLMD Dataset Management
Home-page: 
Author: Thinh Nguyen, Huyen Vu, Dung Huynh
Author-email: nguyenlongthinh@gmail.com, vtphuyen1987@yahoo.com, ducdung8378@gmail.com
License: MIT
Classifier: Intended Audience :: Developers
Classifier: License :: OSI Approved :: MIT License
Classifier: Programming Language :: Python :: 3
Classifier: Operating System :: OS Independent
Requires-Dist: azure-storage-blob
Requires-Dist: requests
Requires-Dist: ml-metadata (==1.0.0)
Requires-Dist: python-dotenv
Requires-Dist: google-cloud-storage
Requires-Dist: mysql-connector-python (==8.0.25)
Requires-Dist: google-cloud-secret-manager
Requires-Dist: google-api-python-client
Requires-Dist: protobuf (==3.19.5)
Requires-Dist: numpy (<=1.23.0)
Requires-Dist: google-cloud-firestore (==2.7.2)
